flask_unittest/__init__.py
flask_unittest/case.py
flask_unittest/loader.py
flask_unittest/main.py
flask_unittest/suite.py
flask_unittest/utils.py
flask_unittest-0.1.3.dist-info/LICENSE
flask_unittest-0.1.3.dist-info/METADATA
flask_unittest-0.1.3.dist-info/WHEEL
flask_unittest-0.1.3.dist-info/top_level.txt
flask_unittest-0.1.3.dist-info/RECORD
