Metadata-Version: 2.1
Name: flask-unittest
Version: 0.1.3
Summary: Unit testing flask applications made easy!
Home-page: https://github.com/TotallyNotChase/flask-unittest
Author: TotallyNotChase
Author-email: totallynotchase42@gmail.com
License: MIT
Platform: any
Classifier: Programming Language :: Python :: 3
Classifier: License :: OSI Approved :: MIT License
Classifier: Operating System :: OS Independent
Classifier: Intended Audience :: Developers
Requires-Python: >=3.6
License-File: LICENSE
